eventlib/__init__.py
eventlib/base.py
eventlib/core.py
eventlib/type_utils.py
eventlib_py-1.0.0.dist-info/LICENSE-APACHE
eventlib_py-1.0.0.dist-info/LICENSE-MIT
eventlib_py-1.0.0.dist-info/METADATA
eventlib_py-1.0.0.dist-info/WHEEL
eventlib_py-1.0.0.dist-info/RECORD
