Metadata-Version: 2.1
Name: eventlib-py
Version: 1.0.0
Summary: A Python event framework to decouple code using events.
License: (Apache-2.0 OR MIT)
Author: Michael Käser
Author-email: info@mickare.de
Requires-Python: >=3.11,<4.0
Classifier: Framework :: AsyncIO
Classifier: License :: OSI Approved :: Apache Software License
Classifier: License :: OSI Approved :: MIT License
Classifier: License :: Other/Proprietary License
Classifier: Operating System :: OS Independent
Classifier: Programming Language :: Python :: 3
Classifier: Programming Language :: Python :: 3.11
Classifier: Programming Language :: Python :: 3.12
Classifier: Topic :: Software Development
Classifier: Topic :: Software Development :: Libraries
Classifier: Typing :: Typed
